fast_targetprice/__init__.py
fast_targetprice_beta-0.0.2.dist-info/METADATA
fast_targetprice_beta-0.0.2.dist-info/WHEEL
fast_targetprice_beta-0.0.2.dist-info/top_level.txt
fast_targetprice_beta-0.0.2.dist-info/RECORD
