Metadata-Version: 2.4
Name: fast_targetprice_beta
Version: 0.0.2
Summary: Lấy giá csgo
Author-email: Minh nguyen <email@example.com>
